chatbot_utils/__init__.py
chatbot_utils/const.py
chatbot_utils/constants.py
chatbot_utils/format_tokens.py
chatbot_utils/redict.py
chatbot_utils/responder.py
chatbot_utils/utils.py
tests/__init__.py
tests/test_chatbot_utils/__init__.py
tests/test_chatbot_utils/test_context.py
tests/test_chatbot_utils/test_redict.py
tests/test_chatbot_utils/test_responder.py
chatbot_utils-1.1.0.dist-info/LICENSE
chatbot_utils-1.1.0.dist-info/METADATA
chatbot_utils-1.1.0.dist-info/WHEEL
chatbot_utils-1.1.0.dist-info/top_level.txt
chatbot_utils-1.1.0.dist-info/RECORD
