Metadata-Version: 2.1
Name: chatbot-utils
Version: 1.1.0
Summary: Tools for creating chatbots
Home-page: http://github.com/eriknyquist/chatbot_utils
Author: Erik Nyquist
Author-email: eknyquist@gmail.com
License: Apache 2.0
Platform: UNKNOWN
